shabanapackage/__init__.py
shabanapackage-0.1.dist-info/LICENSE.txt
shabanapackage-0.1.dist-info/METADATA
shabanapackage-0.1.dist-info/WHEEL
shabanapackage-0.1.dist-info/top_level.txt
shabanapackage-0.1.dist-info/RECORD
