Metadata-Version: 2.1
Name: shabanapackage
Version: 0.1
Summary: This is Very Basic package including some basic functions
Author: Shabana
Author-email: shabanadevelopers786@gmail.com
Classifier: Programming Language :: Python :: 3
Classifier: License :: OSI Approved :: MIT License
Classifier: Operating System :: OS Independent
License-File: LICENSE.txt
